MANIFEST.in
NEWS.txt
README.rst
setup.py
pythrust/__init__.py
pythrust/api.py
pythrust/base.py
pythrust/window.py
pythrust.egg-info/PKG-INFO
pythrust.egg-info/SOURCES.txt
pythrust.egg-info/dependency_links.txt
pythrust.egg-info/not-zip-safe
pythrust.egg-info/requires.txt
pythrust.egg-info/top_level.txt