Metadata-Version: 1.0
Name: pythrust
Version: 0.7.5
Summary: Python language bindings for Thrust
Home-page: https://github.com/breach/pythrust
Author: Stanislas Polu
Author-email: polu.stanislas@gmail.com
License: MIT
Keywords: thrust application shell framework chromium content module python
Platform: UNKNOWN
